mcp_client_jupyter_chat/__init__.py
mcp_client_jupyter_chat/_version.py
mcp_client_jupyter_chat-0.1.7.data/data/etc/jupyter/jupyter_server_config.d/mcp_client_jupyter_chat.json
mcp_client_jupyter_chat-0.1.7.data/data/share/jupyter/labextensions/mcp-client-jupyter-chat/package.json
mcp_client_jupyter_chat-0.1.7.data/data/share/jupyter/labextensions/mcp-client-jupyter-chat/schemas/mcp-client-jupyter-chat/package.json.orig
mcp_client_jupyter_chat-0.1.7.data/data/share/jupyter/labextensions/mcp-client-jupyter-chat/schemas/mcp-client-jupyter-chat/plugin.json
mcp_client_jupyter_chat-0.1.7.data/data/share/jupyter/labextensions/mcp-client-jupyter-chat/static/414.88dd1f734f3007e572a6.js
mcp_client_jupyter_chat-0.1.7.data/data/share/jupyter/labextensions/mcp-client-jupyter-chat/static/526.2a05c8e4512b459bf61c.js
mcp_client_jupyter_chat-0.1.7.data/data/share/jupyter/labextensions/mcp-client-jupyter-chat/static/642.146a8d9809eeb5254761.js
mcp_client_jupyter_chat-0.1.7.data/data/share/jupyter/labextensions/mcp-client-jupyter-chat/static/728.3c3a14cb46aded16e7e7.js
mcp_client_jupyter_chat-0.1.7.data/data/share/jupyter/labextensions/mcp-client-jupyter-chat/static/remoteEntry.2587ebe9837117d32d44.js
mcp_client_jupyter_chat-0.1.7.data/data/share/jupyter/labextensions/mcp-client-jupyter-chat/static/style.js
mcp_client_jupyter_chat-0.1.7.data/data/share/jupyter/labextensions/mcp-client-jupyter-chat/static/third-party-licenses.json
mcp_client_jupyter_chat-0.1.7.data/data/share/jupyter/labextensions/mcp-client-jupyter-chat/install.json
mcp_client_jupyter_chat-0.1.7.dist-info/METADATA
mcp_client_jupyter_chat-0.1.7.dist-info/WHEEL
mcp_client_jupyter_chat-0.1.7.dist-info/licenses/LICENSE
mcp_client_jupyter_chat-0.1.7.dist-info/RECORD
