Metadata-Version: 2.4
Name: mcp_client_jupyter_chat
Version: 0.1.7
Summary: A JupyterLab extension for Chat with AI supporting MCP
Project-URL: Homepage, https://github.com/ihrpr/mcp-client-jupyter-chat
Project-URL: Bug Tracker, https://github.com/ihrpr/mcp-client-jupyter-chat/issues
Project-URL: Repository, https://github.com/ihrpr/mcp-client-jupyter-chat.git
Author-email: Inna <inna.hrpr@gmail.com>
License: BSD 3-Clause License
License-File: LICENSE
Keywords: jupyter,jupyterlab,jupyterlab-extension
Classifier: Framework :: Jupyter
Classifier: Framework :: Jupyter :: JupyterLab
Classifier: Framework :: Jupyter :: JupyterLab :: 4
Classifier: Framework :: Jupyter :: JupyterLab :: Extensions
Classifier: Framework :: Jupyter :: JupyterLab :: Extensions :: Prebuilt
Classifier: License :: OSI Approved :: BSD License
Classifier: Programming Language :: Python
Classifier: Programming Language :: Python :: 3
Classifier: Programming Language :: Python :: 3.9
Classifier: Programming Language :: Python :: 3.10
Classifier: Programming Language :: Python :: 3.11
Classifier: Programming Language :: Python :: 3.12
Classifier: Programming Language :: Python :: 3.13
Requires-Python: >=3.8
Requires-Dist: mcp-server-jupyter>=0.1.9
